odoo/addons/purchase_analytic_tag/README.rst
odoo/addons/purchase_analytic_tag/__init__.py
odoo/addons/purchase_analytic_tag/__manifest__.py
odoo/addons/purchase_analytic_tag/i18n/es.po
odoo/addons/purchase_analytic_tag/i18n/it.po
odoo/addons/purchase_analytic_tag/i18n/purchase_analytic_tag.pot
odoo/addons/purchase_analytic_tag/models/__init__.py
odoo/addons/purchase_analytic_tag/models/purchase_order_line.py
odoo/addons/purchase_analytic_tag/readme/CONTRIBUTORS.md
odoo/addons/purchase_analytic_tag/readme/DESCRIPTION.md
odoo/addons/purchase_analytic_tag/static/description/icon.png
odoo/addons/purchase_analytic_tag/static/description/index.html
odoo/addons/purchase_analytic_tag/tests/__init__.py
odoo/addons/purchase_analytic_tag/tests/test_purchase_analytic_tag.py
odoo/addons/purchase_analytic_tag/views/purchase_oder_view.xml
odoo_addon_purchase_analytic_tag-18.0.1.0.0.2.dist-info/METADATA
odoo_addon_purchase_analytic_tag-18.0.1.0.0.2.dist-info/WHEEL
odoo_addon_purchase_analytic_tag-18.0.1.0.0.2.dist-info/top_level.txt
odoo_addon_purchase_analytic_tag-18.0.1.0.0.2.dist-info/RECORD
